github_heatmap/__init__.py
github_heatmap/__main__.py
github_heatmap/circluar_drawer.py
github_heatmap/cli.py
github_heatmap/config.py
github_heatmap/drawer.py
github_heatmap/err.py
github_heatmap/poster.py
github_heatmap/structures.py
github_heatmap/utils.py
github_heatmap/html_parser/__init__.py
github_heatmap/html_parser/github_parser.py
github_heatmap/html_parser/gitlab_parser.py
github_heatmap/html_parser/jike_parse.py
github_heatmap/html_parser/kindle_parser.py
github_heatmap/loader/__init__.py
github_heatmap/loader/apple_health_loader.py
github_heatmap/loader/base_loader.py
github_heatmap/loader/bbdc_loader.py
github_heatmap/loader/bilibili_loader.py
github_heatmap/loader/chatgpt_loader.py
github_heatmap/loader/cichang_loader.py
github_heatmap/loader/config.py
github_heatmap/loader/covid_loader.py
github_heatmap/loader/dota2_loader.py
github_heatmap/loader/duolingo_loader.py
github_heatmap/loader/forest_loader.py
github_heatmap/loader/from_github_issue_loader.py
github_heatmap/loader/garmin_loader.py
github_heatmap/loader/github_loader.py
github_heatmap/loader/gitlab_loader.py
github_heatmap/loader/gpx_loader.py
github_heatmap/loader/jike_loader.py
github_heatmap/loader/json_loader.py
github_heatmap/loader/kindle_loader.py
github_heatmap/loader/leetcode_loader.py
github_heatmap/loader/multiple_loader.py
github_heatmap/loader/neodb_loader.py
github_heatmap/loader/notion_loader.py
github_heatmap/loader/nrc_loader.py
github_heatmap/loader/ns_loader.py
github_heatmap/loader/openlanguage_loader.py
github_heatmap/loader/shanbay_loader.py
github_heatmap/loader/strava_loader.py
github_heatmap/loader/summary_loader.py
github_heatmap/loader/todoist_loader.py
github_heatmap/loader/wakatime_loader.py
github_heatmap/loader/weread_loader.py
github_heatmap/loader/youtube_loader.py
github_heatmap/skyline/__init__.py
github_heatmap/skyline/config.py
github_heatmap/skyline/skyline.py
github_heatmap/skyline/font/__init__.py
tests/__init__.py
tests/test_poster_utils.py
github_heatmap-1.3.8.dist-info/LICENSE
github_heatmap-1.3.8.dist-info/METADATA
github_heatmap-1.3.8.dist-info/WHEEL
github_heatmap-1.3.8.dist-info/entry_points.txt
github_heatmap-1.3.8.dist-info/top_level.txt
github_heatmap-1.3.8.dist-info/RECORD
