Metadata-Version: 2.1
Name: github_heatmap
Version: 1.3.8
Summary: Make everything a GitHub svg poster and Skyline!
Home-page: https://github.com/malinkang/GitHubPoster
Author: malinkang
Author-email: linkang.ma@gmail.com
License: MIT
License-File: LICENSE
Requires-Dist: requests
Requires-Dist: svgwrite
Requires-Dist: pendulum==3.1.0
Requires-Dist: colour
Provides-Extra: all
Requires-Dist: twint-fork; extra == "all"
Requires-Dist: garminconnect; extra == "all"
Requires-Dist: gpxpy; extra == "all"
Requires-Dist: stravalib; extra == "all"
Requires-Dist: PyGithub; extra == "all"
Requires-Dist: sdf-fork; extra == "all"
Requires-Dist: pandas; extra == "all"
Provides-Extra: garmin
Requires-Dist: garminconnect; extra == "garmin"
Provides-Extra: github
Requires-Dist: PyGithub; extra == "github"
Provides-Extra: gpx
Requires-Dist: gpxpy; extra == "gpx"
Provides-Extra: skyline
Requires-Dist: sdf-fork; extra == "skyline"
Provides-Extra: strava
Requires-Dist: stravalib; extra == "strava"
Provides-Extra: todoist
Requires-Dist: pandas; extra == "todoist"
